web_data_extraction/__init__.py
web_data_extraction/web_data_extraction.py
web_data_extraction-0.0.3.dist-info/METADATA
web_data_extraction-0.0.3.dist-info/WHEEL
web_data_extraction-0.0.3.dist-info/RECORD
