Metadata-Version: 2.1
Name: web-data-extraction
Version: 0.0.3
Summary: A unified collection of web data premises eg Apartment for sale, apartment for rent, house for sale, house for rent
Home-page: https://github.com/ILisa250/web-data-extraction
License: MIT
Keywords: web-data-extraction,web-scraping,Lisa
Author: Lisa Yvette INYANGE
Author-email: linyange@andrew.cmu.edu
Requires-Python: >=3.9,<4.0
Classifier: License :: OSI Approved :: MIT License
Classifier: Programming Language :: Python :: 3
Classifier: Programming Language :: Python :: 3.9
Classifier: Programming Language :: Python :: 3.10
Classifier: Programming Language :: Python :: 3.11
Project-URL: Repository, https://github.com/ILisa250/web-data-extraction
